{"data": {"obj_MajorAxisLength_quantile750": "35.4194306461", "obj_Centroid_quantile975": "999.92", "obj_BoundingBox_median": "50.25", "color_G_quantile250": "0.291930135021", "color_G_quantile750": "0.57691600818", "obj_Perimeter_kurtosis": "26.6575261243", "obj_MinorAxisLength_mean": "36.6893894641", "obj_BoundingBox_skewness": "1.19499344025", "L1_200": "0.0142830484474", "obj_Orientation_std": "53.2373050696", "obj_FilledArea_kurtosis": "63.404496302", "color_B_quantile750": "0.587326081343", "obj_MinorAxisLength_quantile025": "2.97313070228", "obj_Centroid_kurtosis": "1.76294521577", "color_G_mean": "0.435407804701", "color_B_quantile025": "0.220690388745", "color_H_kurtosis": "2.76136748847", "obj_FilledArea_quantile025": "9.0", "obj_EquivDiameter_quantile975": "392.65336556", "color_gray_quantile975": "0.818921022162", "color_H_quantile750": "0.660216887977", "color_gray_quantile025": "0.139063181666", "obj_WeightedCentroid_quantile975": "992.565316089", "obj_MajorAxisLength_skewness": "4.77307740405", "L1_150": "0.618647695782", "obj_Eccentricity_median": "0.799763121192", "texture_denth_2": "1.01578039569", "obj_phase_congruency_max_moment_quantile250": "0.000120369575704", "texture_svarh_1": "44.8698967953", "texture_svarh_2": "45.3359852832", "color_H_std": "0.231509445512", "texture_inf2h_1": "0.829330161438", "obj_phase_congruency_max_moment_mean": "0.0295843882064", "texture_inf2h_2": "0.882568484867", "obj_ConvexArea_std": "105625.461055", "color_R_kurtosis": "2.46324726676", "obj_EquivDiameter_quantile750": "22.3407677025", "obj_Extent_mean": "0.537277601353", "color_gray_quantile250": "0.29685788951", "color_correlation_9": "0.593501171625", "obj_MajorAxisLength_mean": "70.0488458454", "obj_EulerNumber_quantile750": "1.0", "color_R_quantile975": "0.857893740776", "obj_FilledArea_std": "77381.3114482", "texture_entro_2": "3.28198171738", "color_correlation_1": "0.905882549089", "obj_MajorAxisLength_median": "17.7652250628", "color_correlation_4": "0.706992264634", "obj_WeightedCentroid_mean": "0.0", "color_H_quantile975": "0.817062163387", "obj_Centroid_quantile750": "809.199439098", "obj_Eccentricity_quantile250": "0.768495356859", "obj_Extent_quantile250": "0.473653395785", "obj_Extent_kurtosis": "3.23653269595", "LIGHT_FEAT_NUM": "45.0", "color_G_quantile975": "0.814597056448", "obj_Eccentricity_mean": "0.792760121825", "texture_savgh_2": "8.05251605252", "obj_phase_congruency_min_moment_mean": "0.00500684328459", "obj_phase_congruency_orientation_std": "47.227182933", "obj_phase_congruency_orientation_quantile250": "50.0", "obj_ConvexArea_quantile750": "521.0", "obj_Centroid_quantile025": "1.55555555556", "obj_Perimeter_median": "46.2842712475", "obj_Solidity_quantile750": "0.981132075472", "obj_phase_congruency_min_moment_skewness": "5.75761185986", "obj_FilledArea_mean": "13046.1282051", "obj_EquivDiameter_skewness": "5.58971701339", "obj_phase_congruency_orientation_mean": "87.0864560015", "obj_MajorAxisLength_quantile025": "4.7609522857", "obj_Orientation_quantile750": "28.1701473074", "color_S_median": "0.191781231566", "obj_phase_congruency_ft_median": "0.0294068383853", "obj_Eccentricity_std": "0.125991326017", "obj_phase_congruency_orientation_median": "85.0", "obj_MinorAxisLength_quantile750": "18.1738274057", "texture_corrm_1": "0.820535971693", "texture_homop_2": "0.714311979769", "texture_homop_1": "0.651319611513", "color_homogeneity_1": "0.819884769318", "color_B_median": "0.467133334864", "color_B_mean": "0.477038603811", "obj_EulerNumber_quantile975": "1.0", "obj_ConvexArea_quantile025": "9.0", "color_S_quantile025": "0.0453532556879", "color_B_skewness": "0.119095375286", "obj_ConvexArea_median": "132.5", "color_V_kurtosis": "2.45848806721", "obj_Perimeter_quantile250": "19.8994949366", "color_R_median": "0.384478963", "obj_WeightedCentroid_kurtosis": "2.4561611704", "obj_Centroid_median": "424.838992643", "color_G_std": "0.192230632407", "texture_inf1h_1": "-0.28841961172", "obj_Area_quantile975": "125843.4", "color_V_quantile250": "0.370738624382", "texture_indnc_2": "0.932875670338", "obj_MinorAxisLength_skewness": "5.57181803743", "obj_Centroid_mean": "466.651574253", "texture_sosvh_1": "20.2777311369", "obj_Eccentricity_kurtosis": "6.4081559193", "obj_WeightedCentroid_quantile250": "228.777777778", "obj_phase_congruency_orientation_skewness": "0.1134213407", "obj_WeightedCentroid_quantile025": "41.1556526666", "obj_phase_congruency_orientation_quantile025": "6.0", "L1_240": "0.00458738026359", "texture_autoc_1": "19.6554516555", "color_R_skewness": "0.594922147148", "obj_BoundingBox_kurtosis": "3.01908332548", "obj_BoundingBox_quantile750": "427.0", "obj_EulerNumber_mean": "0.371794871795", "obj_Eccentricity_quantile975": "0.970472015656", "color_H_mean": "0.524552638128", "L1_160": "0.0147111507169", "obj_phase_congruency_ft_quantile025": "-1.40133431007", "obj_FilledArea_quantile250": "31.0", "obj_phase_congruency_min_moment_median": "0.000235952052212", "obj_FilledArea_quantile975": "134291.05", "texture_indnc_1": "0.914945574553", "texture_inf1h_2": "-0.373859314808", "color_contrast_9": "1.89842462144", "obj_MinorAxisLength_quantile250": "5.16334010536", "texture_maxpr_2": "0.0929160929161", "texture_senth_1": "2.61655925487", "texture_senth_2": "2.63152359103", "obj_Extent_skewness": "-0.970245047065", "obj_FilledArea_median": "114.5", "color_R_std": "0.203522551968", "obj_phase_congruency_orientation_kurtosis": "2.06460237068", "obj_phase_congruency_max_moment_kurtosis": "11.9031408128", "color_V_std": "0.172091163795", "color_S_quantile975": "0.491499082927", "texture_maxpr_1": "0.0771430771431", "color_gray_median": "0.406743696647", "color_B_kurtosis": "2.26765511343", "obj_phase_congruency_ft_quantile975": "1.39468117104", "color_R_quantile250": "0.275618996924", "texture_contr_1": "1.51554851555", "texture_contr_2": "0.965724965725", "obj_Perimeter_quantile975": "5336.81955931", "color_S_std": "0.116811545411", "obj_phase_congruency_min_moment_std": "0.0125203714368", "obj_Area_quantile750": "392.0", "texture_cprom_1": "549.046703942", "L1_100": "0.233679973096", "obj_phase_congruency_ft_mean": "0.012419646131", "obj_EulerNumber_std": "4.51867402215", "obj_FilledArea_quantile750": "392.0", "color_gray_mean": "0.437507795195", "obj_Orientation_median": "-19.6458989025", "obj_Orientation_mean": "-4.6389731692", "color_V_median": "0.470144156034", "obj_Area_std": "76969.3040552", "obj_Perimeter_quantile025": "9.65685424949", "obj_Solidity_quantile025": "0.446087652502", "texture_dvarh_1": "1.51554851555", "obj_Centroid_skewness": "0.243012250167", "color_V_quantile750": "0.611551374257", "obj_ConvexArea_quantile975": "206273.45", "color_B_quantile250": "0.369606016541", "FEAT_NUM": "78.0", "obj_Centroid_quantile250": "192.096326319", "color_V_quantile975": "0.858072498744", "texture_sosvh_2": "20.3104692634", "obj_ConvexArea_mean": "18590.2307692", "obj_MajorAxisLength_quantile250": "8.08290376865", "obj_Perimeter_mean": "366.156516359", "obj_EulerNumber_median": "1.0", "color_R_mean": "0.426553799814", "texture_energ_1": "0.0398180652691", "obj_Area_skewness": "7.77391979199", "texture_energ_2": "0.0476633360976", "texture_dissi_2": "0.634932634933", "obj_phase_congruency_max_moment_quantile025": "5e-05", "color_S_quantile750": "0.280423822646", "L1_110": "1.99581477641e-06", "obj_MinorAxisLength_std": "108.057175815", "texture_autoc_2": "19.9565289565", "obj_phase_congruency_max_moment_skewness": "2.59511340262", "color_V_mean": "0.496652348589", "color_H_median": "0.621972250144", "obj_BoundingBox_quantile025": "0.5", "color_H_skewness": "-1.04798131106", "obj_Solidity_mean": "0.829154876079", "color_homogeneity_9": "0.636991894522", "texture_savgh_1": "8.04756104756", "color_energy_1": "0.0893242661109", "obj_phase_congruency_max_moment_quantile975": "0.164350628716", "obj_Perimeter_std": "1249.37442919", "obj_Perimeter_quantile750": "121.882250994", "obj_WeightedCentroid_std": "0.0", "color_V_quantile025": "0.221047250261", "color_energy_9": "0.0497952397813", "color_gray_skewness": "0.408414079187", "obj_MinorAxisLength_kurtosis": "36.9177589225", "obj_EulerNumber_skewness": "-8.08463564128", "L1_210": "2.99372216462e-06", "obj_Centroid_std": "337.493658319", "obj_Orientation_quantile250": "-40.9517236245", "obj_FilledArea_skewness": "7.67604733413", "texture_dvarh_2": "0.965724965725", "obj_phase_congruency_max_moment_std": "0.0465579143774", "obj_phase_congruency_orientation_quantile750": "123.0", "obj_Eccentricity_quantile750": "0.873891342169", "obj_BoundingBox_quantile250": "11.0", "obj_EquivDiameter_quantile250": "6.28254931431", "obj_EquivDiameter_quantile025": "3.38513750129", "color_gray_std": "0.189190560614", "texture_idmnc_2": "0.985931601439", "obj_EulerNumber_quantile025": "-4.4", "color_S_mean": "0.212601377467", "obj_MajorAxisLength_quantile975": "788.240376656", "texture_cshad_2": "27.8542373773", "texture_cshad_1": "29.4731438483", "DARK_FEAT_NUM": "33.0", "color_entropy": "7.51087439508", "obj_EquivDiameter_kurtosis": "37.2557411522", "color_gray_kurtosis": "2.3025062308", "color_S_kurtosis": "3.76489175677", "color_B_quantile975": "0.749201152789", "obj_MinorAxisLength_median": "9.61161145247", "texture_denth_1": "1.19046822744", "color_contrast_4": "1.3687561082", "obj_Eccentricity_skewness": "-1.51690676333", "color_H_quantile250": "0.509802034931", "obj_phase_congruency_ft_std": "0.868893444419", "color_S_skewness": "0.890937302805", "color_R_quantile025": "0.127994654373", "texture_corrm_2": "0.885811450279", "obj_Area_kurtosis": "64.7583910621", "color_G_median": "0.406114456558", "obj_Orientation_quantile975": "90.0", "color_contrast_1": "0.439719712288", "obj_phase_congruency_ft_quantile750": "0.796324839788", "obj_Orientation_quantile025": "-83.2474630075", "obj_EquivDiameter_mean": "41.956415508", "texture_idmnc_1": "0.978482728975", "obj_EquivDiameter_median": "12.0741555758", "color_energy_4": "0.0562339227846", "color_V_skewness": "0.434889178961", "obj_BoundingBox_mean": "246.932692308", "color_S_quantile250": "0.12373271934", "texture_dissi_1": "0.828363828364", "obj_ConvexArea_quantile250": "32.0", "obj_phase_congruency_ft_quantile250": "-0.770814590055", "color_gray_quantile750": "0.569822640022", "obj_phase_congruency_ft_skewness": "-0.034250252233", "obj_WeightedCentroid_median": "0.0", "obj_Orientation_kurtosis": "2.21020091612", "color_H_quantile025": "0.064882926049", "obj_EulerNumber_kurtosis": "68.5650534416", "obj_Orientation_skewness": "0.547308179623", "obj_phase_congruency_min_moment_quantile250": "-5e-05", "obj_Solidity_quantile250": "0.713675213675", "texture_corrp_1": "0.820535971693", "texture_corrp_2": "0.885811450279", "obj_Area_quantile250": "31.0", "obj_phase_congruency_min_moment_kurtosis": "60.6166679583", "obj_MajorAxisLength_kurtosis": "26.8856069245", "obj_Solidity_skewness": "-0.96485464927", "obj_ConvexArea_skewness": "7.46427838047", "color_R_quantile750": "0.552652130767", "L1_250": "0.114012914917", "obj_Extent_quantile025": "0.258180418719", "obj_MinorAxisLength_quantile975": "349.249684972", "obj_MajorAxisLength_std": "193.859544958", "texture_cprom_2": "570.7898839", "obj_phase_congruency_min_moment_quantile750": "0.00417580724059", "obj_Extent_std": "0.134164893655", "obj_Extent_quantile975": "0.7325", "obj_WeightedCentroid_skewness": "0.529150050621", "texture_homom_1": "0.676581973011", "obj_Solidity_kurtosis": "2.80450039581", "texture_homom_2": "0.728546108308", "obj_WeightedCentroid_quantile750": "595.710843373", "color_homogeneity_4": "0.682389654697", "texture_entro_1": "3.45374042116", "color_G_skewness": "0.350480805102", "obj_phase_congruency_max_moment_median": "0.00878366250031", "color_B_std": "0.145708087774", "obj_Area_quantile025": "9.0", "color_G_quantile025": "0.125460635031", "obj_EulerNumber_quantile250": "1.0", "obj_phase_congruency_min_moment_quantile025": "-5e-05", "obj_EquivDiameter_std": "121.595492616", "obj_Perimeter_skewness": "4.84867592869", "L1_255": "1.99581477641e-06", "obj_ConvexArea_kurtosis": "60.6235015119", "obj_Solidity_median": "0.889756944444", "color_G_kurtosis": "2.23904577187", "obj_BoundingBox_quantile975": "996.2", "phase_congruency_noise_thresh": "0.0400290177582", "obj_Extent_median": "0.579545454545", "obj_Area_median": "114.5", "obj_BoundingBox_std": "326.552047656", "obj_Area_mean": "12846.1666667", "obj_phase_congruency_max_moment_quantile750": "0.0399896806215", "obj_Solidity_quantile975": "1.0", "obj_Extent_quantile750": "0.630303030303", "obj_phase_congruency_ft_kurtosis": "1.72165314177", "obj_phase_congruency_min_moment_quantile975": "0.0396639067381", "obj_Solidity_std": "0.172951578803", "obj_phase_congruency_orientation_quantile975": "174.0", "obj_Eccentricity_quantile025": "0.42071503589"}}