{"data": {"obj_MajorAxisLength_quantile750": "30.0897800664", "obj_Centroid_quantile975": "1000.44444444", "obj_BoundingBox_median": "21.0", "color_G_quantile250": "0.322528456862", "color_G_quantile750": "0.480599547964", "obj_Perimeter_kurtosis": "106.966041025", "obj_MinorAxisLength_mean": "20.8540833451", "obj_BoundingBox_skewness": "1.16841424741", "L1_200": "3.99162955283e-06", "obj_Orientation_std": "52.2783263271", "obj_FilledArea_kurtosis": "110.995281697", "color_B_quantile750": "0.510491611122", "obj_MinorAxisLength_quantile025": "2.97313070228", "obj_Centroid_kurtosis": "1.34805446666", "color_G_mean": "0.406791885628", "color_B_quantile025": "0.246783011655", "color_H_kurtosis": "17.8398130673", "obj_FilledArea_quantile025": "9.0", "obj_EquivDiameter_quantile975": "60.4841652837", "color_gray_quantile975": "0.671390204298", "color_H_quantile750": "0.618049668884", "color_gray_quantile025": "0.191183886668", "obj_WeightedCentroid_quantile975": "994.737864078", "obj_MajorAxisLength_skewness": "9.72438971405", "L1_150": "0.99990819252", "obj_Eccentricity_median": "0.840352527182", "texture_denth_2": "1.46834799978", "obj_phase_congruency_max_moment_quantile250": "5e-05", "texture_svarh_1": "36.3473292014", "texture_svarh_2": "36.2903606554", "color_H_std": "0.0908848100686", "texture_inf2h_1": "0.459971455816", "obj_phase_congruency_max_moment_mean": "0.0122024877248", "texture_inf2h_2": "0.433334263458", "obj_ConvexArea_std": "93403.9230368", "color_R_kurtosis": "3.52150832647", "obj_EquivDiameter_quantile750": "17.6618177595", "obj_Extent_mean": "0.536801943376", "color_gray_quantile250": "0.319662638236", "color_correlation_9": "0.147799466873", "obj_MajorAxisLength_mean": "33.7916028036", "obj_EulerNumber_quantile750": "1.0", "color_R_quantile975": "0.658425852802", "obj_FilledArea_std": "91125.0192609", "texture_entro_2": "3.66062996326", "color_correlation_1": "0.672747983617", "obj_MajorAxisLength_median": "14.5599644788", "color_correlation_4": "0.262151504227", "obj_WeightedCentroid_mean": "0.0", "color_H_quantile975": "0.721987473907", "obj_Centroid_quantile750": "954.553191489", "obj_Eccentricity_quantile250": "0.778979349883", "obj_Extent_quantile250": "0.442276560245", "obj_Extent_kurtosis": "3.05763536513", "LIGHT_FEAT_NUM": "6.0", "color_G_quantile975": "0.676572914609", "obj_Eccentricity_mean": "0.820953123651", "texture_savgh_2": "7.7612967613", "obj_phase_congruency_min_moment_mean": "0.00138853377303", "obj_phase_congruency_orientation_std": "50.0111839399", "obj_phase_congruency_orientation_quantile250": "36.0", "obj_ConvexArea_quantile750": "298.75", "obj_Centroid_quantile025": "1.57222222222", "obj_Perimeter_median": "37.6984848098", "obj_Solidity_quantile750": "1.0", "obj_phase_congruency_min_moment_skewness": "7.34110709911", "obj_FilledArea_mean": "8867.59292035", "obj_EquivDiameter_skewness": "10.2321920476", "obj_phase_congruency_orientation_mean": "76.2062492952", "obj_MajorAxisLength_quantile025": "4.7609522857", "obj_Orientation_quantile750": "0.0", "color_S_median": "0.145102858744", "obj_phase_congruency_ft_median": "-0.0888245361164", "obj_Eccentricity_std": "0.125927921738", "obj_phase_congruency_orientation_median": "64.0", "obj_MinorAxisLength_quantile750": "12.7978724275", "texture_corrm_1": "0.447680085528", "texture_homop_2": "0.499046943281", "texture_homop_1": "0.508085031289", "color_homogeneity_1": "0.754808350982", "color_B_median": "0.434860432426", "color_B_mean": "0.442534365493", "obj_EulerNumber_quantile975": "1.0", "obj_ConvexArea_quantile025": "9.0", "color_S_quantile025": "0.0231217063398", "color_B_skewness": "0.417937276765", "obj_ConvexArea_median": "82.0", "color_V_kurtosis": "3.48160306712", "obj_Perimeter_quantile250": "18.4852813742", "color_R_median": "0.370446296801", "obj_WeightedCentroid_kurtosis": "1.53981022807", "obj_Centroid_median": "458.614986854", "color_G_std": "0.121784523061", "texture_inf1h_1": "-0.0631438528966", "obj_Area_quantile975": "2898.6", "color_V_quantile250": "0.36633661489", "texture_indnc_2": "0.869442364703", "obj_MinorAxisLength_skewness": "10.2974827862", "obj_Centroid_mean": "484.566875311", "texture_sosvh_1": "17.6591584558", "obj_Eccentricity_kurtosis": "5.55052533515", "obj_WeightedCentroid_quantile250": "21.1430313675", "obj_phase_congruency_orientation_skewness": "0.507398276223", "obj_WeightedCentroid_quantile025": "6.77173913043", "obj_phase_congruency_orientation_quantile025": "5.0", "L1_240": "3.99162955283e-06", "texture_autoc_1": "16.274967275", "color_R_skewness": "0.530954934944", "obj_BoundingBox_kurtosis": "2.64323567359", "obj_BoundingBox_quantile750": "449.0", "obj_EulerNumber_mean": "0.867256637168", "obj_Eccentricity_quantile975": "0.972484278636", "color_H_mean": "0.590311491316", "L1_160": "0.0", "obj_phase_congruency_ft_quantile025": "-1.39591617111", "obj_FilledArea_quantile250": "25.75", "obj_phase_congruency_min_moment_median": "-5e-05", "obj_FilledArea_quantile975": "2898.925", "texture_indnc_1": "0.872505682718", "texture_inf1h_2": "-0.0552449150818", "color_contrast_9": "1.72571503374", "obj_MinorAxisLength_quantile250": "4.63519249533", "texture_maxpr_2": "0.0682250682251", "texture_senth_1": "2.4253436962", "texture_senth_2": "2.41828346429", "obj_Extent_skewness": "-0.195279699907", "obj_FilledArea_median": "75.0", "color_R_std": "0.12408707353", "obj_phase_congruency_orientation_kurtosis": "2.12374213086", "obj_phase_congruency_max_moment_kurtosis": "16.7985971651", "color_V_std": "0.111989653249", "color_S_quantile975": "0.381959184402", "texture_maxpr_1": "0.0694350694351", "color_gray_median": "0.393448665378", "color_B_kurtosis": "3.27601730834", "obj_phase_congruency_ft_quantile975": "1.36308120009", "color_R_quantile250": "0.295508349691", "texture_contr_1": "3.00825700826", "texture_contr_2": "3.15035215035", "obj_Perimeter_quantile975": "526.914081402", "color_S_std": "0.0910764102445", "obj_phase_congruency_min_moment_std": "0.00484399283281", "obj_Area_quantile750": "245.0", "texture_cprom_1": "185.78375326", "L1_100": "8.98116649386e-06", "obj_phase_congruency_ft_mean": "-0.058633337734", "obj_EulerNumber_std": "0.411973143602", "obj_FilledArea_quantile750": "245.75", "color_gray_mean": "0.403193047367", "obj_Orientation_median": "-35.3523796507", "obj_Orientation_mean": "-17.5896919451", "color_V_median": "0.43522762649", "obj_Area_std": "91125.0479495", "obj_Perimeter_quantile025": "9.65685424949", "obj_Solidity_quantile025": "0.574322671864", "texture_dvarh_1": "3.00825700826", "obj_Centroid_skewness": "0.0550408434824", "color_V_quantile750": "0.51134494635", "obj_ConvexArea_quantile975": "3913.425", "color_B_quantile250": "0.36612408786", "FEAT_NUM": "113.0", "obj_Centroid_quantile250": "16.0576540755", "color_V_quantile975": "0.691067415712", "texture_sosvh_2": "17.6622254901", "obj_ConvexArea_mean": "9209.65486726", "obj_MajorAxisLength_quantile250": "7.98034294477", "obj_Perimeter_mean": "153.947475262", "obj_EulerNumber_median": "1.0", "color_R_mean": "0.38112005616", "texture_energ_1": "0.0344723033776", "obj_Area_skewness": "10.487532884", "texture_energ_2": "0.0338805724021", "texture_dissi_2": "1.3346043346", "obj_phase_congruency_max_moment_quantile025": "5e-05", "color_S_quantile750": "0.206794962209", "L1_110": "1.99581477641e-06", "obj_MinorAxisLength_std": "103.969276581", "texture_autoc_2": "16.2074862075", "obj_phase_congruency_max_moment_skewness": "3.22602789265", "color_V_mean": "0.443662315937", "color_H_median": "0.598110412784", "obj_BoundingBox_quantile025": "0.5", "color_H_skewness": "-2.48863570193", "obj_Solidity_mean": "0.868638614796", "color_homogeneity_9": "0.613844157801", "texture_savgh_1": "7.76036176036", "color_energy_1": "0.117966769202", "obj_phase_congruency_max_moment_quantile975": "0.0841972250448", "obj_Perimeter_std": "817.012812478", "obj_Perimeter_quantile750": "80.487067043", "obj_WeightedCentroid_std": "0.0", "color_V_quantile025": "0.246956794839", "color_energy_9": "0.0846763625137", "color_gray_skewness": "0.496562701181", "obj_MinorAxisLength_kurtosis": "108.319181382", "obj_EulerNumber_skewness": "-3.22787030694", "L1_210": "0.0", "obj_Centroid_std": "405.772605004", "obj_Orientation_quantile250": "-52.4074568495", "obj_FilledArea_skewness": "10.4875320462", "texture_dvarh_2": "3.15035215035", "obj_phase_congruency_max_moment_std": "0.0237963237727", "obj_phase_congruency_orientation_quantile750": "114.0", "obj_Eccentricity_quantile750": "0.915588273871", "obj_BoundingBox_quantile250": "5.0", "obj_EquivDiameter_quantile250": "5.72569450268", "obj_EquivDiameter_quantile025": "3.38513750129", "color_gray_std": "0.120675578501", "texture_idmnc_2": "0.957391464903", "obj_EulerNumber_quantile025": "-0.675", "color_S_mean": "0.157974451858", "obj_MajorAxisLength_quantile975": "99.3002541569", "texture_cshad_2": "8.16884203092", "texture_cshad_1": "8.66739947042", "DARK_FEAT_NUM": "107.0", "color_entropy": "6.96062475176", "obj_EquivDiameter_kurtosis": "107.39583712", "color_gray_kurtosis": "3.4234701037", "color_S_kurtosis": "5.11278420548", "color_B_quantile975": "0.683490691649", "obj_MinorAxisLength_median": "7.01095454602", "texture_denth_1": "1.44981567055", "color_contrast_4": "1.49508376612", "obj_Eccentricity_skewness": "-1.40880821307", "color_H_quantile250": "0.577233023276", "obj_phase_congruency_ft_std": "0.843464723528", "color_S_skewness": "1.0933278942", "color_R_quantile025": "0.164208482767", "texture_corrm_2": "0.421578130801", "obj_Area_kurtosis": "110.995293338", "color_G_median": "0.39719617508", "obj_Orientation_quantile975": "90.0", "color_contrast_1": "0.663370774226", "obj_phase_congruency_ft_quantile750": "0.684570756958", "obj_Orientation_quantile025": "-84.9147745801", "obj_EquivDiameter_mean": "23.7840121423", "texture_idmnc_1": "0.959153471493", "obj_EquivDiameter_median": "9.77205023806", "color_energy_4": "0.0882996220678", "color_V_skewness": "0.488345231709", "obj_BoundingBox_mean": "249.219026549", "color_S_quantile250": "0.0929824735446", "texture_dissi_1": "1.29821729822", "obj_ConvexArea_quantile250": "26.75", "obj_phase_congruency_ft_quantile250": "-0.809080689612", "color_gray_quantile750": "0.476103907761", "obj_phase_congruency_ft_skewness": "0.0736505674544", "obj_WeightedCentroid_median": "0.0", "obj_Orientation_kurtosis": "2.99336080489", "color_H_quantile025": "0.317425982396", "obj_EulerNumber_kurtosis": "13.0072459245", "obj_Orientation_skewness": "1.0117698035", "obj_phase_congruency_min_moment_quantile250": "-5e-05", "obj_Solidity_quantile250": "0.793955454467", "texture_corrp_1": "0.447680085528", "texture_corrp_2": "0.421578130801", "obj_Area_quantile250": "25.75", "obj_phase_congruency_min_moment_kurtosis": "88.4501429803", "obj_MajorAxisLength_kurtosis": "100.131859944", "obj_Solidity_skewness": "-0.854902042523", "obj_ConvexArea_skewness": "10.4860435338", "color_R_quantile750": "0.455220776039", "L1_250": "0.0", "obj_Extent_quantile025": "0.265085565476", "obj_MinorAxisLength_quantile975": "54.339189403", "obj_MajorAxisLength_std": "109.776716991", "texture_cprom_2": "178.60450982", "obj_phase_congruency_min_moment_quantile750": "0.000414799442725", "obj_Extent_std": "0.133943438925", "obj_Extent_quantile975": "0.75", "obj_WeightedCentroid_skewness": "0.236957002383", "texture_homom_1": "0.556507479127", "obj_Solidity_kurtosis": "2.97189721608", "texture_homom_2": "0.549315157648", "obj_WeightedCentroid_quantile750": "828.58066151", "color_homogeneity_4": "0.637995886019", "texture_entro_1": "3.64581503334", "color_G_skewness": "0.485590723196", "obj_phase_congruency_max_moment_median": "0.0009413890864", "color_B_std": "0.110241272892", "obj_Area_quantile025": "9.0", "color_G_quantile025": "0.192422034315", "obj_EulerNumber_quantile250": "1.0", "obj_phase_congruency_min_moment_quantile025": "-5e-05", "obj_EquivDiameter_std": "104.020325266", "obj_Perimeter_skewness": "10.2034168472", "L1_255": "1.99581477641e-06", "obj_ConvexArea_kurtosis": "110.974522207", "obj_Solidity_median": "0.886075949367", "color_G_kurtosis": "3.40744954102", "obj_BoundingBox_quantile975": "997.5", "phase_congruency_noise_thresh": "0.0768542551275", "obj_Extent_median": "0.571428571429", "obj_Area_median": "75.0", "obj_BoundingBox_std": "369.342106468", "obj_Area_mean": "8867.26548673", "obj_phase_congruency_max_moment_quantile750": "0.0134236863949", "obj_Solidity_quantile975": "1.0", "obj_Extent_quantile750": "0.621948401479", "obj_phase_congruency_ft_kurtosis": "1.77022046795", "obj_phase_congruency_min_moment_quantile975": "0.0139040233057", "obj_Solidity_std": "0.1261124396", "obj_phase_congruency_orientation_quantile975": "175.0", "obj_Eccentricity_quantile025": "0.479438637664"}}