{"data": {"obj_MajorAxisLength_quantile750": "107.924703782", "obj_Centroid_quantile975": "999.446666667", "obj_BoundingBox_median": "106.0", "color_G_quantile250": "0.350138664251", "color_G_quantile750": "0.549181594873", "obj_Perimeter_kurtosis": "41.1822920947", "obj_MinorAxisLength_mean": "49.7404843659", "obj_BoundingBox_skewness": "0.91059395856", "L1_200": "0.354633333899", "obj_Orientation_std": "68.4707222367", "obj_FilledArea_kurtosis": "51.1200620595", "color_B_quantile750": "0.50919942951", "obj_MinorAxisLength_quantile025": "2.97313070228", "obj_Centroid_kurtosis": "1.8894769773", "color_G_mean": "0.447452969194", "color_B_quantile025": "0.221561577136", "color_H_kurtosis": "2.80775554547", "obj_FilledArea_quantile025": "9.0", "obj_EquivDiameter_quantile975": "396.067529451", "color_gray_quantile975": "0.689146390946", "color_H_quantile750": "0.509855134355", "color_gray_quantile025": "0.203804532645", "obj_WeightedCentroid_quantile975": "992.959161593", "obj_MajorAxisLength_skewness": "3.41937645725", "L1_150": "0.147647383437", "obj_Eccentricity_median": "0.902114704718", "texture_denth_2": "1.02578783387", "obj_phase_congruency_max_moment_quantile250": "5e-05", "texture_svarh_1": "53.3387778939", "texture_svarh_2": "53.0287246631", "color_H_std": "0.300550441381", "texture_inf2h_1": "0.894935590875", "obj_phase_congruency_max_moment_mean": "0.024807040137", "texture_inf2h_2": "0.8625061015", "obj_ConvexArea_std": "104080.508239", "color_R_kurtosis": "2.32301784965", "obj_EquivDiameter_quantile750": "39.9203572028", "obj_Extent_mean": "0.521891630183", "color_gray_quantile250": "0.354607199992", "color_correlation_9": "0.576370418613", "obj_MajorAxisLength_mean": "121.59424569", "obj_EulerNumber_quantile750": "1.0", "color_R_quantile975": "0.730326667042", "obj_FilledArea_std": "53086.5967036", "texture_entro_2": "3.27600204693", "color_correlation_1": "0.880254652813", "obj_MajorAxisLength_median": "32.2796979715", "color_correlation_4": "0.705339441051", "obj_WeightedCentroid_mean": "0.0", "color_H_quantile975": "0.974605137399", "obj_Centroid_quantile750": "784.616089774", "obj_Eccentricity_quantile250": "0.781801828077", "obj_Extent_quantile250": "0.40655593341", "obj_Extent_kurtosis": "2.99598987065", "LIGHT_FEAT_NUM": "61.0", "color_G_quantile975": "0.681778109075", "obj_Eccentricity_mean": "0.85730934567", "texture_savgh_2": "8.98063798064", "obj_phase_congruency_min_moment_mean": "0.00386979269211", "obj_phase_congruency_orientation_std": "57.1186146615", "obj_phase_congruency_orientation_quantile250": "38.0", "obj_ConvexArea_quantile750": "2429.75", "obj_Centroid_quantile025": "1.9380952381", "obj_Perimeter_median": "95.9827560573", "obj_Solidity_quantile750": "0.916150846364", "obj_phase_congruency_min_moment_skewness": "7.11662824226", "obj_FilledArea_mean": "11870.9213483", "obj_EquivDiameter_skewness": "4.21201757186", "obj_phase_congruency_orientation_mean": "92.0487045422", "obj_MajorAxisLength_quantile025": "4.7609522857", "obj_Orientation_quantile750": "73.7954270565", "color_S_median": "0.126144197397", "obj_phase_congruency_ft_median": "0.0309550003717", "obj_Eccentricity_std": "0.155254488288", "obj_phase_congruency_orientation_median": "94.0", "obj_MinorAxisLength_quantile750": "24.7589119164", "texture_corrm_1": "0.877621687688", "texture_homop_2": "0.721901270036", "texture_homop_1": "0.763276872131", "color_homogeneity_1": "0.875434329693", "color_B_median": "0.417990985412", "color_B_mean": "0.427210035967", "obj_EulerNumber_quantile975": "1.0", "obj_ConvexArea_quantile025": "9.0", "color_S_quantile025": "0.0162159892397", "color_B_skewness": "0.188982790489", "obj_ConvexArea_median": "286.0", "color_V_kurtosis": "2.33293046677", "obj_Perimeter_quantile250": "38.0416305603", "color_R_median": "0.476406927401", "obj_WeightedCentroid_kurtosis": "2.18689838208", "obj_Centroid_median": "475.550013092", "color_G_std": "0.131251742047", "texture_inf1h_1": "-0.40791008126", "obj_Area_quantile975": "125089.7", "color_V_quantile250": "0.377456086684", "texture_indnc_2": "0.933930664933", "obj_MinorAxisLength_skewness": "4.78464608692", "obj_Centroid_mean": "518.510688255", "texture_sosvh_1": "23.3704751984", "obj_Eccentricity_kurtosis": "12.3353214023", "obj_WeightedCentroid_quantile250": "321.656565657", "obj_phase_congruency_orientation_skewness": "-0.0699011110905", "obj_WeightedCentroid_quantile025": "15.980081377", "obj_phase_congruency_orientation_quantile025": "2.0", "L1_240": "0.00824570874875", "texture_autoc_1": "23.1046991047", "color_R_skewness": "-0.0450580430047", "obj_BoundingBox_kurtosis": "2.49384567181", "obj_BoundingBox_quantile750": "481.5", "obj_EulerNumber_mean": "0.0786516853933", "obj_Eccentricity_quantile975": "0.998580701444", "color_H_mean": "0.264475333192", "L1_160": "0.00542761828446", "obj_phase_congruency_ft_quantile025": "-1.41075894914", "obj_FilledArea_quantile250": "74.0", "obj_phase_congruency_min_moment_median": "-2.43979776343e-05", "obj_FilledArea_quantile975": "145166.225", "texture_indnc_1": "0.944447468035", "texture_inf1h_2": "-0.344245110078", "color_contrast_9": "1.04490947383", "obj_MinorAxisLength_quantile250": "5.77160886628", "texture_maxpr_2": "0.0973740973741", "texture_senth_1": "2.59727052936", "texture_senth_2": "2.60473230584", "obj_Extent_skewness": "-0.258799417503", "obj_FilledArea_median": "199.0", "color_R_std": "0.147166728326", "obj_phase_congruency_orientation_kurtosis": "1.63908414992", "obj_phase_congruency_max_moment_kurtosis": "17.4413080269", "color_V_std": "0.139903251208", "color_S_quantile975": "0.236122433451", "texture_maxpr_1": "0.107685107685", "color_gray_median": "0.448973199299", "color_B_kurtosis": "2.89218497411", "obj_phase_congruency_ft_quantile975": "1.41534292984", "color_R_quantile250": "0.362878562901", "texture_contr_1": "0.821197821198", "texture_contr_2": "1.05459405459", "obj_Perimeter_quantile975": "5648.4264442", "color_S_std": "0.0633235421572", "obj_phase_congruency_min_moment_std": "0.0116851838211", "obj_Area_quantile750": "1251.75", "texture_cprom_1": "339.008279448", "L1_100": "0.237615719836", "obj_phase_congruency_ft_mean": "0.0153939169128", "obj_EulerNumber_std": "5.02996638137", "obj_FilledArea_quantile750": "1251.75", "color_gray_mean": "0.453641750675", "obj_Orientation_median": "0.0", "obj_Orientation_mean": "0.295349522787", "color_V_median": "0.477242559132", "obj_Area_std": "51483.5032349", "obj_Perimeter_quantile025": "9.65685424949", "obj_Solidity_quantile025": "0.240449638638", "texture_dvarh_1": "0.821197821198", "obj_Centroid_skewness": "0.0187115670154", "color_V_quantile750": "0.593121432914", "obj_ConvexArea_quantile975": "229513.075", "color_B_quantile250": "0.350008458866", "FEAT_NUM": "89.0", "obj_Centroid_quantile250": "283.542635659", "color_V_quantile975": "0.731415061796", "texture_sosvh_2": "23.3789392381", "obj_ConvexArea_mean": "22143.8426966", "obj_MajorAxisLength_quantile250": "14.5585223322", "obj_Perimeter_mean": "626.092835637", "obj_EulerNumber_median": "1.0", "color_R_mean": "0.475876768837", "texture_energ_1": "0.0585743248756", "obj_Area_skewness": "7.07226476216", "texture_energ_2": "0.0509103735337", "texture_dissi_2": "0.63170963171", "obj_phase_congruency_max_moment_quantile025": "5e-05", "color_S_quantile750": "0.175305582783", "L1_110": "1.39707034349e-05", "obj_MinorAxisLength_std": "128.707738139", "texture_autoc_2": "22.9934539935", "obj_phase_congruency_max_moment_skewness": "3.27733983395", "color_V_mean": "0.482621996332", "color_H_median": "0.0906787306615", "obj_BoundingBox_quantile025": "0.5", "color_H_skewness": "1.16875613139", "obj_Solidity_mean": "0.748680295368", "color_homogeneity_9": "0.724945441187", "texture_savgh_1": "8.98000998001", "color_energy_1": "0.150839842162", "obj_phase_congruency_max_moment_quantile975": "0.164401009609", "obj_Perimeter_std": "1943.4692257", "obj_Perimeter_quantile750": "346.460461481", "obj_WeightedCentroid_std": "0.0", "color_V_quantile025": "0.227279670343", "color_energy_9": "0.087861698862", "color_gray_skewness": "0.00989837883807", "obj_MinorAxisLength_kurtosis": "28.8010665886", "obj_EulerNumber_skewness": "-5.98573528615", "L1_210": "0.00222233975354", "obj_Centroid_std": "308.855020017", "obj_Orientation_quantile250": "-72.836664568", "obj_FilledArea_skewness": "6.68572027523", "texture_dvarh_2": "1.05459405459", "obj_phase_congruency_max_moment_std": "0.0467120032644", "obj_phase_congruency_orientation_quantile750": "145.0", "obj_Eccentricity_quantile750": "0.965415319608", "obj_BoundingBox_quantile250": "14.0", "obj_EquivDiameter_quantile250": "9.70601064426", "obj_EquivDiameter_quantile025": "3.38513750129", "color_gray_std": "0.132928391713", "texture_idmnc_2": "0.985218784744", "obj_EulerNumber_quantile025": "-18.375", "color_S_mean": "0.124824522698", "obj_MajorAxisLength_quantile975": "717.593917617", "texture_cshad_2": "-0.0197123913371", "texture_cshad_1": "0.087130992638", "DARK_FEAT_NUM": "28.0", "color_entropy": "7.09872692381", "obj_EquivDiameter_kurtosis": "23.7510608951", "color_gray_kurtosis": "2.42767014801", "color_S_kurtosis": "3.18436155297", "color_B_quantile975": "0.639929426805", "obj_MinorAxisLength_median": "10.2887793621", "texture_denth_1": "0.92870891484", "color_contrast_4": "0.726132411877", "obj_Eccentricity_skewness": "-2.47334246863", "color_H_quantile250": "0.0672407435042", "obj_phase_congruency_ft_std": "0.876099159783", "color_S_skewness": "0.225404142787", "color_R_quantile025": "0.198021404562", "texture_corrm_2": "0.842962933669", "obj_Area_kurtosis": "56.8328002774", "color_G_median": "0.442581780537", "obj_Orientation_quantile975": "90.0", "color_contrast_1": "0.294985068182", "obj_phase_congruency_ft_quantile750": "0.800548502796", "obj_Orientation_quantile025": "-89.3109608318", "obj_EquivDiameter_mean": "53.1737786101", "texture_idmnc_1": "0.988403079779", "obj_EquivDiameter_median": "15.9177469952", "color_energy_4": "0.104319618762", "color_V_skewness": "0.0467059230611", "obj_BoundingBox_mean": "280.56741573", "color_S_quantile250": "0.073133272438", "texture_dissi_1": "0.525715525716", "obj_ConvexArea_quantile250": "91.75", "obj_phase_congruency_ft_quantile250": "-0.773279815209", "color_gray_quantile750": "0.557501269997", "obj_phase_congruency_ft_skewness": "-0.0265123560154", "obj_WeightedCentroid_median": "0.0", "obj_Orientation_kurtosis": "1.40298691774", "color_H_quantile025": "0.01738814075", "obj_EulerNumber_kurtosis": "39.7308871114", "obj_Orientation_skewness": "0.0200392749593", "obj_phase_congruency_min_moment_quantile250": "-5e-05", "obj_Solidity_quantile250": "0.632316204407", "texture_corrp_1": "0.877621687688", "texture_corrp_2": "0.842962933669", "obj_Area_quantile250": "74.0", "obj_phase_congruency_min_moment_kurtosis": "91.8481770597", "obj_MajorAxisLength_kurtosis": "17.6583101486", "obj_Solidity_skewness": "-0.666623754952", "obj_ConvexArea_skewness": "7.28685738893", "color_R_quantile750": "0.592600097496", "L1_250": "0.244121078099", "obj_Extent_quantile025": "0.119973402854", "obj_MinorAxisLength_quantile975": "478.312783829", "obj_MajorAxisLength_std": "220.052921891", "texture_cprom_2": "326.171190465", "obj_phase_congruency_min_moment_quantile750": "0.00217033593824", "obj_Extent_std": "0.189403121678", "obj_Extent_quantile975": "0.908173076923", "obj_WeightedCentroid_skewness": "0.0772537181363", "texture_homom_1": "0.772642208356", "obj_Solidity_kurtosis": "2.97162231263", "texture_homom_2": "0.735802377469", "obj_WeightedCentroid_quantile750": "697.842287695", "color_homogeneity_4": "0.775664745428", "texture_entro_1": "3.14954690857", "color_G_skewness": "0.0269374212383", "obj_phase_congruency_max_moment_median": "0.00363388428366", "color_B_std": "0.111346631632", "obj_Area_quantile025": "9.0", "color_G_quantile025": "0.201181143113", "obj_EulerNumber_quantile250": "1.0", "obj_phase_congruency_min_moment_quantile025": "-5e-05", "obj_EquivDiameter_std": "107.879572059", "obj_Perimeter_skewness": "5.82943593123", "L1_255": "1.99581477641e-06", "obj_ConvexArea_kurtosis": "60.0383707412", "obj_Solidity_median": "0.777777777778", "color_G_kurtosis": "2.46880348789", "obj_BoundingBox_quantile975": "994.7", "phase_congruency_noise_thresh": "0.0407601305357", "obj_Extent_median": "0.542780748663", "obj_Area_median": "199.0", "obj_BoundingBox_std": "322.633799658", "obj_Area_mean": "11258.4382022", "obj_phase_congruency_max_moment_quantile750": "0.0284014440449", "obj_Solidity_quantile975": "1.0", "obj_Extent_quantile750": "0.645692881", "obj_phase_congruency_ft_kurtosis": "1.72985184291", "obj_phase_congruency_min_moment_quantile975": "0.0346710660218", "obj_Solidity_std": "0.200070908174", "obj_phase_congruency_orientation_quantile975": "178.0", "obj_Eccentricity_quantile025": "0.475224802987"}}